CHANGELOG.rst
LICENSE.txt
MANIFEST.in
README.rst
setup.cfg
setup.py
config_manager/__init__.py
config_manager/config_manager.py
config_manager/config_ruleset.py
config_manager.egg-info/PKG-INFO
config_manager.egg-info/SOURCES.txt
config_manager.egg-info/dependency_links.txt
config_manager.egg-info/requires.txt
config_manager.egg-info/top_level.txt
config_manager/test/__init__.py
config_manager/test/test_config_manager.py
config_manager/test/test_config_ruleset.py