Metadata-Version: 2.1
Name: config-manager
Version: 1.1.2
Summary: A basic configuration reader and manager for python projects
Home-page: https://github.com/afxentios/config-manager
Author: Afxentios Hadjiminas
Author-email: afxentios@hadjimina.com
License: MIT
Keywords: configuration,management
Platform: UNKNOWN
Classifier: Development Status :: 5 - Production/Stable
Classifier: Intended Audience :: Developers
Classifier: License :: OSI Approved :: MIT License
Classifier: Operating System :: OS Independent
Classifier: Programming Language :: Python
Classifier: Programming Language :: Python :: 2.7
Classifier: Programming Language :: Python :: 3
Classifier: Programming Language :: Python :: 3.6
Classifier: Programming Language :: Python :: 3.7
Classifier: Topic :: Software Development :: Libraries
Classifier: Topic :: Software Development :: Libraries :: Python Modules
Provides-Extra: test
